data_analysis/__init__.py
data_analysis/analyze.py
data_analysis/clean.py
data_analysis/plot.py
data_analysis/plot_model.py
data_analysis/process.py
data_analysis/structs.py
data_analysis/summary.py
data_analysis/utils.py
data_analysis_helpers-0.1.5.dist-info/LICENSE
data_analysis_helpers-0.1.5.dist-info/METADATA
data_analysis_helpers-0.1.5.dist-info/WHEEL
data_analysis_helpers-0.1.5.dist-info/top_level.txt
data_analysis_helpers-0.1.5.dist-info/RECORD
