Metadata-Version: 2.1
Name: data-analysis-helpers
Version: 0.1.5
Summary: Data Science helpers
Home-page: https://github.com/ShivnarenSrinivasan/data_analysis
Author: Shivnaren Srinivasan
Author-email: shivnaren@gmail.com
Project-URL: Bug Tracker, https://github.com/ShivnarenSrinivasan/data_analysis/issues
Classifier: Programming Language :: Python :: 3
Classifier: License :: OSI Approved :: MIT License
Classifier: Operating System :: OS Independent
Requires-Python: >=3.7
License-File: LICENSE
Requires-Dist: numpy
Requires-Dist: pandas
Requires-Dist: matplotlib
Requires-Dist: seaborn
Requires-Dist: scikit-learn
Requires-Dist: requests
